{
  "version": "v2026-02-28",
  "sex": "F",
  "equipment": "All",
  "ipf_weight_class": "76",
  "age_class": "35-39",
  "tested": "all",
  "lift": "total",
  "hist": {
    "file": "hist/f/all/76/35-39/all/total.bin",
    "base_bin_size_kg": 2.5,
    "min_kg": 117.5,
    "max_kg": 692.5,
    "bins": 230,
    "total": 3363
  },
  "heat": {
    "file": "heat/f/all/76/35-39/all/total.bin",
    "x_base_bin_size_kg": 2.5,
    "y_base_bin_size_kg": 1.0,
    "min_x_kg": 117.5,
    "max_x_kg": 692.5,
    "min_y_kg": 69.0,
    "max_y_kg": 77.0,
    "width": 230,
    "height": 8,
    "total": 3363
  }
}