{"version":"v2026-03-03","sex":"M","equipment":"Multi-ply","ipf_weight_class":"120+","age_class":"18-19","tested":"all","lift":"total","metric":"Kg","hist":{"file":"hist/m/multi-ply/120_/18-19/all/kg/total.bin","base_bin_size_kg":2.5,"min_kg":422.5,"max_kg":1102.5,"bins":272,"total":103},"heat":{"file":"heat/m/multi-ply/120_/18-19/all/kg/total.bin","x_base_bin_size_kg":2.5,"y_base_bin_size_kg":1.0,"min_x_kg":422.5,"max_x_kg":1102.5,"min_y_kg":120.0,"max_y_kg":200.0,"width":272,"height":80,"total":103}}