{"version":"v2026-03-06","sex":"M","equipment":"Multi-ply","ipf_weight_class":"105","age_class":"24-34","tested":"all","lift":"squat","metric":"Kg","hist":{"file":"hist/m/multi-ply/105/24-34/all/kg/squat.bin","base_bin_size_kg":2.5,"min_kg":32.5,"max_kg":512.5,"bins":192,"total":1220},"heat":{"file":"heat/m/multi-ply/105/24-34/all/kg/squat.bin","x_base_bin_size_kg":2.5,"y_base_bin_size_kg":1.0,"min_x_kg":32.5,"max_x_kg":512.5,"min_y_kg":93.0,"max_y_kg":106.0,"width":192,"height":13,"total":1220}}