{"version":"v2026-03-03","sex":"M","equipment":"Multi-ply","ipf_weight_class":"93","age_class":"55-59","tested":"tested","lift":"total","metric":"Wilks","hist":{"file":"hist/m/multi-ply/93/55-59/tested/wilks/total.bin","base_bin_size_kg":2.5,"min_kg":230.0,"max_kg":512.5,"bins":113,"total":21},"heat":{"file":"heat/m/multi-ply/93/55-59/tested/wilks/total.bin","x_base_bin_size_kg":2.5,"y_base_bin_size_kg":1.0,"min_x_kg":230.0,"max_x_kg":512.5,"min_y_kg":84.0,"max_y_kg":93.0,"width":113,"height":9,"total":21}}